dict_plugin/__init__.py
dict_plugin/src/_dict_plugin/__init__.py
dict_plugin/src/_dict_plugin/_base.py
dict_plugin-0.1.1.dist-info/LICENSE
dict_plugin-0.1.1.dist-info/METADATA
dict_plugin-0.1.1.dist-info/WHEEL
dict_plugin-0.1.1.dist-info/RECORD
