Metadata-Version: 2.1
Name: dict_plugin
Version: 0.1.1
Summary: 
License: MIT
Author: Mohamed Martini
Author-email: mhdmart1@gmail.com
Requires-Python: >=3.8
Classifier: License :: OSI Approved :: MIT License
Classifier: Programming Language :: Python :: 3
Classifier: Programming Language :: Python :: 3.8
Classifier: Programming Language :: Python :: 3.9
Classifier: Programming Language :: Python :: 3.10
Classifier: Programming Language :: Python :: 3.11
Classifier: Programming Language :: Python :: 3.12
Requires-Dist: pydantic (>=2.7.1,<3.0.0)
